harmatz/__init__.py
yehonatan/__init__.py
yehonatan-0.0.3.dist-info/LICENSE
yehonatan-0.0.3.dist-info/METADATA
yehonatan-0.0.3.dist-info/WHEEL
yehonatan-0.0.3.dist-info/top_level.txt
yehonatan-0.0.3.dist-info/RECORD
