Metadata-Version: 2.1
Name: yehonatan
Version: 0.0.3
Summary: my python package
Home-page: https://github.com/yehonatanHarmatz/yehonatan
Author: Yehonatan Harmatz
Author-email: yehonatan.y@gmail.com
License: UNKNOWN
Project-URL: Bug Tracker, https://github.com/yehonatanHarmatz/yehonatan/issues
Platform: UNKNOWN
Classifier: Programming Language :: Python :: 3
Classifier: License :: OSI Approved :: MIT License
Classifier: Operating System :: OS Independent
Requires-Python: >=3.6
License-File: LICENSE
